coop_bar/__init__.py
coop_bar/apps.py
coop_bar/bar.py
coop_bar/urls.py
coop_bar/utils.py
coop_bar/static/css/coop_bar.css
coop_bar/templates/coop_bar.html
coop_bar/templatetags/__init__.py
coop_bar/templatetags/coop_bar_tags.py
apidev_coop_bar-1.6.1.dist-info/METADATA
apidev_coop_bar-1.6.1.dist-info/WHEEL
apidev_coop_bar-1.6.1.dist-info/top_level.txt
apidev_coop_bar-1.6.1.dist-info/RECORD
