Metadata-Version: 2.1
Name: apidev-coop-bar
Version: 1.6.1
Summary: Pluggable admin bar system , works well with coop_cms
Home-page: https://github.com/ljean/coop-bar/
Download-URL: https://github.com/ljean/coop-bar/tarball/master
Author: Luc Jean
Author-email: ljean@apidev.fr
License: BSD
Classifier: Development Status :: 4 - Beta
Classifier: Environment :: Web Environment
Classifier: Intended Audience :: Developers
Classifier: License :: OSI Approved :: BSD License
Classifier: Operating System :: OS Independent
Classifier: Programming Language :: Python
Classifier: Framework :: Django
Classifier: Natural Language :: English
Classifier: Natural Language :: French
Classifier: Topic :: Internet :: WWW/HTTP :: Dynamic Content
Classifier: Topic :: Internet :: WWW/HTTP :: WSGI :: Application
